Metadata-Version: 2.1
Name: baseapp-django-trench
Version: 0.4.4
Summary: REST Multi-factor authentication package for Django
Home-page: https://github.com/silverlogic/django-trench
Author: Merixstudio
Author-email: trench@merixstudio.com
License: MIT License
Classifier: Framework :: Django
Classifier: Framework :: Django :: 2.0
Classifier: Framework :: Django :: 2.1
Classifier: Framework :: Django :: 2.2
Classifier: Framework :: Django :: 3.0
Classifier: Framework :: Django :: 3.1
Classifier: Framework :: Django :: 3.2
Classifier: Framework :: Django :: 4.0
Classifier: Framework :: Django :: 4.1
Classifier: Intended Audience :: Developers
Classifier: License :: OSI Approved :: MIT License
Classifier: Operating System :: OS Independent
Classifier: Programming Language :: Python
Classifier: Programming Language :: Python :: 3.7
Classifier: Programming Language :: Python :: 3.8
Classifier: Programming Language :: Python :: 3.9
Classifier: Programming Language :: Python :: 3.10
Classifier: Programming Language :: Python :: 3.11
License-File: LICENSE
License-File: AUTHORS
Requires-Dist: pyotp >=2.6.0
Requires-Dist: twilio >=6.56.0
Requires-Dist: yubico-client >=1.13.0
Requires-Dist: boto3 >=1.21.37
Requires-Dist: smsapi-client >=2.4.5
Provides-Extra: docs
Requires-Dist: sphinx >=1.4 ; extra == 'docs'
Requires-Dist: sphinx-rtd-theme ; extra == 'docs'
